{
  "name": "booster_pack_soul",
  "pulls": [
    {
      "weight": 929,
      "entries": [
        {
          "count": 8,
          "rarities": [
            "Common"
          ]
        },
        {
          "count": 1,
          "rarities": [
            "Rare"
          ]
        }
      ]
    },
    {
      "weight": 276,
      "entries": [
        {
          "count": 7,
          "rarities": [
            "Common"
          ]
        },
        {
          "count": 1,
          "rarities": [
            "Rare"
          ]
        },
        {
          "count": 1,
          "rarities": [
            "Super Rare"
          ]
        }
      ]
    },
    {
      "weight": 115,
      "entries": [
        {
          "count": 7,
          "rarities": [
            "Common"
          ]
        },
        {
          "count": 1,
          "rarities": [
            "Rare"
          ]
        },
        {
          "count": 1,
          "rarities": [
            "Ultra Rare"
          ]
        }
      ]
    },
    {
      "weight": 60,
      "entries": [
        {
          "count": 7,
          "rarities": [
            "Common"
          ]
        },
        {
          "count": 1,
          "rarities": [
            "Rare"
          ]
        },
        {
          "count": 1,
          "rarities": [
            "Soul Rare"
          ]
        }
      ]
    }
  ]
}